LICENSE
README.md
setup.cfg
setup.py
list_cli/__init__.py
list_cli/__main__.py
list_cli/__version__.py
list_cli/processors.py
list_cli/results.py
list_cli.egg-info/PKG-INFO
list_cli.egg-info/SOURCES.txt
list_cli.egg-info/dependency_links.txt
list_cli.egg-info/entry_points.txt
list_cli.egg-info/top_level.txt